<Templates>
  <Environment>

		<Fog>
			<ViewDistance type="Int" value="8000"/>
			<ViewDistanceLowSpec type="Int" value="1000"/>
			<LDRGlobalDensMult type="Float" value="1.0"/>
		</Fog>

		<Terrain>
			<DetailLayersViewDistRatio type="Float" value="1.0"/>
			<HeightMapAO type="BOOL" value="0"/>
			<IntegrateObjects type="BOOL" value="0"/>
			<AutoGenerateBaseTexture type="BOOL" value="0"/>
			<SupportOfflineProceduralVegetation type="BOOL" value="0"/>
		</Terrain>

		<EnvState>
			<ConsoleMergedMeshesPool type="Int" value="2750" />
			<ShowTerrainSurface type="BOOL" value="1"/>
			<SunShadowsMinSpec type="Int" value="1"/>
			<SunShadowsAdditionalCascadeMinSpec type="Int" value="0"/>
			<SunShadowsClipPlaneRange type="Float" value="256.0f"/>
			<SunShadowsClipPlaneRangeShift type="Float" value="0.0f"/>
			<SunShadowsFromTerrain type="BOOL" value="0"/>
			<UseLayersActivation type="BOOL" value="0"/>
		</EnvState>

		<VolFogShadows>
			<Enable type="BOOL" value="0"/>
			<EnableForClouds type="BOOL" value="0"/>
		</VolFogShadows>

		<VolumetricCloud>
			<HorizonHeight type="Float" value="-1000.0"/>
			<MaxViewableDistance type="Float" value="100000.0"/>
			<MaxRayMarchDistance type="Float" value="20000.0"/>
			<ShadingLOD type="Float" value="0.7"/>
			<ShadowTilingSize type="Float" value="16000"/>
			<MaxGlobalCloudDensity type="Float" value="0.04"/>
			<GlobalCloudNoiseVolumeTexture type="Texture" value=""/>
			<GlobalCloudNoiseScale type="Vector" value="3,3,5"/>
			<EdgeTurbulenceNoiseVolumeTexture type="Texture" value=""/>
			<EdgeTurbulenceNoiseScale type="Vector" value="1,1,1"/>
			<EdgeTurbulenceNoiseErode type="BOOL" value="1"/>
			<EdgeTurbulenceNoiseAbsolute type="BOOL" value="1"/>
			<CloudVolumeTexture type="Texture" value=""/>
			<TilingSize type="Vector" value="64000,64000,4000"/>
			<TilingOffset type="Vector" value="0,0,0"/>
			<RemapCloudDensityMin type="Float" value="0.0"/>
			<RemapCloudDensityMax type="Float" value="1.0"/>
			<AdditionalNoiseIntensity type="Float" value="0.2"/>
		</VolumetricCloud>

		<Ocean>
			<Material type="Material" value="%ENGINE%/EngineAssets/Materials/Water/Ocean_default" />
			<CausticDepth type="Float" value="8.0"/>
			<CausticIntensity type="Float" value="1.0"/>
			<CausticsTilling type="Float" value ="1.0"/>
		</Ocean>

		<OceanAnimation>
			<WindDirection type="Float" value="1.0"/>
			<WindSpeed type="Float" value="4.0"/>
			<WavesAmount type="Float" value="1.5"/>
			<WavesSize type="Float" value="0.4"/>
		</OceanAnimation>

		<DynTexSource>
			<Width type="Int" value="256"/>
			<Height type="Int" value="256"/>
		</DynTexSource>

  </Environment>
</Templates>
